Workbook

Sheet Executive Summary
A2: REDWINE.LABEL — ANNUAL PERFORMANCE DASHBOARD
A3: FY 2025-2026 Sales & Warehouse Inventory Report | Generated July 16, 2026
A5: TOTAL REVENUE | D5: TOTAL GROSS PROFIT | G5: TOTAL STOCK ON HAND
A6: =SUM('Sales Ledger'!J2:J501) | D6: =SUM('Sales Ledger'!M2:M501) | G6: =SUM('Warehouse Inventory'!H2:H151)
A9: Warehouse Inventory Breakdown
A10: Warehouse Code | B10: Location | C10: Total SKUs Stocked | D10: Units On Hand | E10: Inventory Value (Cost) | F10: Est. Retail Value
A11: WH-HYD-01 | B11: Hyderabad (Telangana) | C11: =COUNTIF('Warehouse Inventory'!F2:F151, "WH-HYD-01") | D11: =SUMIF('Warehouse Inventory'!F2:F151, "WH-HYD-01", 'Warehouse Inventory'!H2:H151) | E11: =SUMPRODUCT(('Warehouse Inventory'!$F$2:$F$151="WH-HYD-01")*('Warehouse Inventory'!$H$2:$H$151)*('Warehouse Inventory'!$J$2:$J$151)) | F11: =SUMPRODUCT(('Warehouse Inventory'!$F$2:$F$151="WH-HYD-01")*('Warehouse Inventory'!$H$2:$H$151)*('Warehouse Inventory'!$K$2:$K$151))
A12: WH-BLR-02 | B12: Bengaluru (Karnataka) | C12: =COUNTIF('Warehouse Inventory'!F2:F151, "WH-BLR-02") | D12: =SUMIF('Warehouse Inventory'!F2:F151, "WH-BLR-02", 'Warehouse Inventory'!H2:H151) | E12: =SUMPRODUCT(('Warehouse Inventory'!$F$2:$F$151="WH-BLR-02")*('Warehouse Inventory'!$H$2:$H$151)*('Warehouse Inventory'!$J$2:$J$151)) | F12: =SUMPRODUCT(('Warehouse Inventory'!$F$2:$F$151="WH-BLR-02")*('Warehouse Inventory'!$H$2:$H$151)*('Warehouse Inventory'!$K$2:$K$151))
A13: WH-DEL-03 | B13: Delhi NCR (Haryana) | C13: =COUNTIF('Warehouse Inventory'!F2:F151, "WH-DEL-03") | D13: =SUMIF('Warehouse Inventory'!F2:F151, "WH-DEL-03", 'Warehouse Inventory'!H2:H151) | E13: =SUMPRODUCT(('Warehouse Inventory'!$F$2:$F$151="WH-DEL-03")*('Warehouse Inventory'!$H$2:$H$151)*('Warehouse Inventory'!$J$2:$J$151)) | F13: =SUMPRODUCT(('Warehouse Inventory'!$F$2:$F$151="WH-DEL-03")*('Warehouse Inventory'!$H$2:$H$151)*('Warehouse Inventory'!$K$2:$K$151))
A14: Total Network Stock | C14: =SUM(C11:C13) | D14: =SUM(D11:D13) | E14: =SUM(E11:E13) | F14: =SUM(F11:F13)

Sheet Sales Ledger
A1: Order ID | B1: Order Date | C1: SKU | D1: Product ID | E1: Product Name | F1: Category | G1: Size | H1: Quantity Ordered | I1: Unit Retail Price | J1: Total Revenue | K1: Unit Product Cost | L1: Total Cost of Goods | M1: Gross Profit Contribution | N1: Fulfillment Warehouse | O1: Sales Channel
A2: ORD-2025381 | B2: 2025-07-15 | C2: PD-008-XL | D2: PD-008 | E2: Tuscan Sun Silk Skirt | F2: Skirts | G2: XL | H2: 3 | I2: 4500 | J2: =H2*I2 | K2: 1600 | L2: =H2*K2 | M2: =J2-L2 | N2: WH-HYD-01 | O2: Mobile App
A3: ORD-2025058 | B3: 2025-07-16 | C3: PD-005-S | D3: PD-005 | E3: Shiraz Wrap Evening Dress | F3: Dresses | G3: S | H3: 2 | I3: 9200 | J3: =H3*I3 | K3: 3500 | L3: =H3*K3 | M3: =J3-L3 | N3: WH-DEL-03 | O3: Retail Store
A4: ORD-2025266 | B4: 2025-07-16 | C4: PD-004-M | D4: PD-004 | E4: Rosé Off-Shoulder Mini | F4: Dresses | G4: M | H4: 2 | I4: 4900 | J4: =H4*I4 | K4: 1800 | L4: =H4*K4 | M4: =J4-L4 | N4: WH-HYD-01 | O4: Mobile App
A5: ORD-2025298 | B5: 2025-07-18 | C5: PD-003-S | D5: PD-003 | E5: Bordeaux Lace Midi | F5: Dresses | G5: S | H5: 2 | I5: 7800 | J5: =H5*I5 | K5: 2800 | L5: =H5*K5 | M5: =J5-L5 | N5: WH-DEL-03 | O5: Mobile App
A6: ORD-2025052 | B6: 2025-07-19 | C6: PD-009-M | D6: PD-009 | E6: Syrah Pleated Maxi Skirt | F6: Skirts | G6: M | H6: 5 | I6: 5400 | J6: =H6*I6 | K6: 1900 | L6: =H6*K6 | M6: =J6-L6 | N6: WH-BLR-02 | O6: Mobile App
A7: ORD-2025229 | B7: 2025-07-19 | C7: PD-006-XL | D7: PD-006 | E7: Chiffon Crimson Blouse | F7: Tops | G7: XL | H7: 3 | I7: 3200 | J7: =H7*I7 | K7: 1100 | L7: =H7*K7 | M7: =J7-L7 | N7: WH-DEL-03 | O7: Mobile App
A8: ORD-2025135 | B8: 2025-07-21 | C8: PD-006-S | D8: PD-006 | E8: Chiffon Crimson Blouse | F8: Tops | G8: S | H8: 4 | I8: 3200 | J8: =H8*I8 | K8: 1100 | L8: =H8*K8 | M8: =J8-L8 | N8: WH-HYD-01 | O8: Retail Store
A9: ORD-2025032 | B9: 2025-07-22 | C9: PD-002-XS | D9: PD-002 | E9: Merlot Satin Slip Dress | F9: Dresses | G9: XS | H9: 2 | I9: 6200 | J9: =H9*I9 | K9: 2100 | L9: =H9*K9 | M9: =J9-L9 | N9: WH-HYD-01 | O9: Retail Store
A10: ORD-2025386 | B10: 2025-07-23 | C10: PD-005-M | D10: PD-005 | E10: Shiraz Wrap Evening Dress | F10: Dresses | G10: M | H10: 1 | I10: 9200 | J10: =H10*I10 | K10: 3500 | L10: =H10*K10 | M10: =J10-L10 | N10: WH-BLR-02 | O10: Online Store
A11: ORD-2025470 | B11: 2025-07-23 | C11: PD-005-L | D11: PD-005 | E11: Shiraz Wrap Evening Dress | F11: Dresses | G11: L | H11: 3 | I11: 9200 | J11: =H11*I11 | K11: 3500 | L11: =H11*K11 | M11: =J11-L11 | N11: WH-DEL-03 | O11: Online Store
A12: ORD-2025067 | B12: 2025-07-27 | C12: PD-003-S | D12: PD-003 | E12: Bordeaux Lace Midi | F12: Dresses | G12: S | H12: 3 | I12: 7800 | J12: =H12*I12 | K12: 2800 | L12: =H12*K12 | M12: =J12-L12 | N12: WH-BLR-02 | O12: Mobile App
A13: ORD-2025071 | B13: 2025-07-27 | C13: PD-009-M | D13: PD-009 | E13: Syrah Pleated Maxi Skirt | F13: Skirts | G13: M | H13: 2 | I13: 5400 | J13: =H13*I13 | K13: 1900 | L13: =H13*K13 | M13: =J13-L13 | N13: WH-BLR-02 | O13: Retail Store
... A501: ORD-2025431 | B501: 2026-07-13 | C501: PD-003-XL | D501: PD-003 | E501: Bordeaux Lace Midi | F501: Dresses | G501: XL | H501: 3 | I501: 7800 | J501: =H501*I501 | K501: 2800 | L501: =H501*K501 | M501: =J501-L501 | N501: WH-DEL-03 | O501: Retail Store

Sheet Warehouse Inventory
A1: SKU | B1: Product ID | C1: Product Name | D1: Category | E1: Size | F1: Warehouse Code | G1: Fulfillment City | H1: Stock On Hand (Qty) | I1: Safety/Reorder Threshold | J1: Unit Cost (INR) | K1: Unit Price (INR) | L1: Total Asset Value (At Cost) | M1: Inventory Status
A2: PD-001-XS | B2: PD-001 | C2: Cabernet Velvet Gown | D2: Dresses | E2: XS | F2: WH-HYD-01 | G2: Hyderabad (Telangana) | H2: 96 | I2: 30 | J2: 3200 | K2: 8500 | L2: =H2*J2 | M2: =IF(H2<=I2, "REORDER NOW", "HEALTHY")
A3: PD-001-XS | B3: PD-001 | C3: Cabernet Velvet Gown | D3: Dresses | E3: XS | F3: WH-BLR-02 | G3: Bengaluru (Karnataka) | H3: 29 | I3: 30 | J3: 3200 | K3: 8500 | L3: =H3*J3 | M3: =IF(H3<=I3, "REORDER NOW", "HEALTHY")
A4: PD-001-XS | B4: PD-001 | C4: Cabernet Velvet Gown | D4: Dresses | E4: XS | F4: WH-DEL-03 | G4: Delhi NCR (Haryana) | H4: 18 | I4: 30 | J4: 3200 | K4: 8500 | L4: =H4*J4 | M4: =IF(H4<=I4, "REORDER NOW", "HEALTHY")
A5: PD-001-S | B5: PD-001 | C5: Cabernet Velvet Gown | D5: Dresses | E5: S | F5: WH-HYD-01 | G5: Hyderabad (Telangana) | H5: 109 | I5: 30 | J5: 3200 | K5: 8500 | L5: =H5*J5 | M5: =IF(H5<=I5, "REORDER NOW", "HEALTHY")
A6: PD-001-S | B6: PD-001 | C6: Cabernet Velvet Gown | D6: Dresses | E6: S | F6: WH-BLR-02 | G6: Bengaluru (Karnataka) | H6: 50 | I6: 30 | J6: 3200 | K6: 8500 | L6: =H6*J6 | M6: =IF(H6<=I6, "REORDER NOW", "HEALTHY")
A7: PD-001-S | B7: PD-001 | C7: Cabernet Velvet Gown | D7: Dresses | E7: S | F7: WH-DEL-03 | G7: Delhi NCR (Haryana) | H7: 46 | I7: 30 | J7: 3200 | K7: 8500 | L7: =H7*J7 | M7: =IF(H7<=I7, "REORDER NOW", "HEALTHY")
A8: PD-001-M | B8: PD-001 | C8: Cabernet Velvet Gown | D8: Dresses | E8: M | F8: WH-HYD-01 | G8: Hyderabad (Telangana) | H8: 43 | I8: 30 | J8: 3200 | K8: 8500 | L8: =H8*J8 | M8: =IF(H8<=I8, "REORDER NOW", "HEALTHY")
A9: PD-001-M | B9: PD-001 | C9: Cabernet Velvet Gown | D9: Dresses | E9: M | F9: WH-BLR-02 | G9: Bengaluru (Karnataka) | H9: 32 | I9: 30 | J9: 3200 | K9: 8500 | L9: =H9*J9 | M9: =IF(H9<=I9, "REORDER NOW", "HEALTHY")
A10: PD-001-M | B10: PD-001 | C10: Cabernet Velvet Gown | D10: Dresses | E10: M | F10: WH-DEL-03 | G10: Delhi NCR (Haryana) | H10: 109 | I10: 30 | J10: 3200 | K10: 8500 | L10: =H10*J10 | M10: =IF(H10<=I10, "REORDER NOW", "HEALTHY")
A11: PD-001-L | B11: PD-001 | C11: Cabernet Velvet Gown | D11: Dresses | E11: L | F11: WH-HYD-01 | G11: Hyderabad (Telangana) | H11: 28 | I11: 30 | J11: 3200 | K11: 8500 | L11: =H11*J11 | M11: =IF(H11<=I11, "REORDER NOW", "HEALTHY")
A12: PD-001-L | B12: PD-001 | C12: Cabernet Velvet Gown | D12: Dresses | E12: L | F12: WH-BLR-02 | G12: Bengaluru (Karnataka) | H12: 101 | I12: 30 | J12: 3200 | K12: 8500 | L12: =H12*J12 | M12: =IF(H12<=I12, "REORDER NOW", "HEALTHY")
A13: PD-001-L | B13: PD-001 | C13: Cabernet Velvet Gown | D13: Dresses | E13: L | F13: WH-DEL-03 | G13: Delhi NCR (Haryana) | H13: 109 | I13: 30 | J13: 3200 | K13: 8500 | L13: =H13*J13 | M13: =IF(H13<=I13, "REORDER NOW", "HEALTHY")
... A151: PD-010-XL | B151: PD-010 | C151: Noir Tailored Blazer | D151: Outerwear | E151: XL | F151: WH-DEL-03 | G151: Delhi NCR (Haryana) | H151: 80 | I151: 30 | J151: 4200 | K151: 11000 | L151: =H151*J151 | M151: =IF(H151<=I151, "REORDER NOW", "HEALTHY")
